straeto/__init__.py
straeto/straeto.py
straeto/resources/agency.txt
straeto/resources/calendar_dates.txt
straeto/resources/routes.txt
straeto/resources/stop_times.txt
straeto/resources/stopinfo.txt
straeto/resources/stops.txt
straeto/resources/trips.txt
straeto-1.4.1.dist-info/LICENSE.txt
straeto-1.4.1.dist-info/METADATA
straeto-1.4.1.dist-info/WHEEL
straeto-1.4.1.dist-info/top_level.txt
straeto-1.4.1.dist-info/zip-safe
straeto-1.4.1.dist-info/RECORD
